{
  "type": "minecraft:generic",
  "pools": [
    {
      "rolls": {
        "type": "minecraft:uniform",
        "min": 0,
        "max": 0.85
      },
      "entries": [
        {
          "type": "minecraft:item",
          "name": "minecraft:flint"
        },
        {
          "type": "minecraft:item",
          "functions": [
            {
              "function": "minecraft:set_nbt",
              "tag": "{\"genes\": {\"fertility\": {\"dom\": 1, \"rec\": 1}, \"gain\": {\"dom\": 1, \"rec\": 1}, \"growth\": {\"dom\": 1, \"rec\": 1}, \"mutativity\": {\"dom\": 1, \"rec\": 1}, \"resistance\": {\"dom\": 10, \"rec\": 10}, \"species\": {\"dom\": \"minecraft:beetroot\", \"rec\": \"minecraft:beetroot\"}, \"strength\": {\"dom\": 1, \"rec\": 1}}}"
            }
          ],
          "name": "agricraft:seed"
        },
        {
          "type": "minecraft:item",
          "functions": [
            {
              "function": "minecraft:set_nbt",
              "tag": "{\"genes\": {\"fertility\": {\"dom\": 1, \"rec\": 1}, \"gain\": {\"dom\": 1, \"rec\": 1}, \"growth\": {\"dom\": 1, \"rec\": 1}, \"mutativity\": {\"dom\": 1, \"rec\": 1}, \"resistance\": {\"dom\": 10, \"rec\": 10}, \"species\": {\"dom\": \"minecraft:potato\", \"rec\": \"minecraft:potato\"}, \"strength\": {\"dom\": 1, \"rec\": 1}}}"
            }
          ],
          "name": "agricraft:seed"
        },
        {
          "type": "minecraft:item",
          "functions": [
            {
              "function": "minecraft:set_nbt",
              "tag": "{\"genes\": {\"fertility\": {\"dom\": 1, \"rec\": 1}, \"gain\": {\"dom\": 1, \"rec\": 1}, \"growth\": {\"dom\": 1, \"rec\": 1}, \"mutativity\": {\"dom\": 1, \"rec\": 1}, \"resistance\": {\"dom\": 10, \"rec\": 10}, \"species\": {\"dom\": \"minecraft:wheat\", \"rec\": \"minecraft:wheat\"}, \"strength\": {\"dom\": 1, \"rec\": 1}}}"
            }
          ],
          "name": "agricraft:seed"
        }
      ]
    }
  ],
  "random_sequence": "minecraft:gameplay/depleted_soil_till"
}