{
    "items": [
        {
            "id": "agricraft:seed",
            "Count": 1,
            "tag": {
                "genes": {
                    "species": {
                        "dom": "mysticalagriculture:tin",
                        "rec": "mysticalagriculture:tin"
                    }
                }
            }
        },
        {
            "id": "agricraft:seed",
            "Count": 1,
            "tag": {
                "genes": {
                    "fertility": {
                        "dom": 10,
                        "rec": 10
                    },
                    "gain": {
                        "dom": 10,
                        "rec": 10
                    },
                    "growth": {
                        "dom": 10,
                        "rec": 10
                    },
                    "mutativity": {
                        "dom": 10,
                        "rec": 10
                    },
                    "resistance": {
                        "dom": 10,
                        "rec": 10
                    },
                    "species": {
                        "dom": "minecraft:blue_orchid",
                        "rec": "minecraft:blue_orchid"
                    },
                    "strength": {
                        "dom": 10,
                        "rec": 10
                    }
                }
            }
        },
        {
            "id": "agricraft:seed",
            "Count": 1,
            "tag": {
                "genes": {
                    "fertility": {
                        "dom": 10,
                        "rec": 10
                    },
                    "gain": {
                        "dom": 10,
                        "rec": 10
                    },
                    "growth": {
                        "dom": 10,
                        "rec": 10
                    },
                    "mutativity": {
                        "dom": 10,
                        "rec": 10
                    },
                    "resistance": {
                        "dom": 10,
                        "rec": 10
                    },
                    "species": {
                        "dom": "minecraft:oxeye_daisy",
                        "rec": "minecraft:oxeye_daisy"
                    },
                    "strength": {
                        "dom": 10,
                        "rec": 10
                    }
                }
            }
        }
    ],
    "shapes": {
        "wasteland:basic_flower": "enchanted:ritual_chalk",
        "wasteland:advanced_flower": "enchanted:nether_chalk"
    },
    "factory": {
        "type": "enchanted:create_item",
        "items": [
            {
                "id": "agricraft:seed",
                "Count": 1,
                "tag": {
                    "genes": {
                        "fertility": {
                            "dom": 10,
                            "rec": 10
                        },
                        "gain": {
                            "dom": 10,
                            "rec": 10
                        },
                        "growth": {
                            "dom": 10,
                            "rec": 10
                        },
                        "mutativity": {
                            "dom": 10,
                            "rec": 10
                        },
                        "resistance": {
                            "dom": 10,
                            "rec": 10
                        },
                        "species": {
                            "dom": "mysticalagriculture:tin",
                            "rec": "mysticalagriculture:tin"
                        },
                        "strength": {
                            "dom": 10,
                            "rec": 10
                        }
                    }
                }
            }
        ]
    },
    "power": 3500
}